pleasant_promises/__init__.py
pleasant_promises/core.py
pleasant_promises/dataloader.py
pleasant_promises/graphene.py
pleasant_promises-1.1.dist-info/METADATA
pleasant_promises-1.1.dist-info/WHEEL
pleasant_promises-1.1.dist-info/top_level.txt
pleasant_promises-1.1.dist-info/RECORD
