Metadata-Version: 2.1
Name: pleasant-promises
Version: 1.1
Home-page: https://github.com/AlexCLeduc/pleasant-python-promises
Author: AlexCLeduc
Classifier: Programming Language :: Python :: 3
Classifier: License :: OSI Approved :: MIT License
Classifier: Operating System :: OS Independent
